gpt_engineer/__init__.py
gpt_engineer/cli/__init__.py
gpt_engineer/cli/collect.py
gpt_engineer/cli/file_selector.py
gpt_engineer/cli/learning.py
gpt_engineer/cli/main.py
gpt_engineer/core/__init__.py
gpt_engineer/core/ai.py
gpt_engineer/core/chat_to_files.py
gpt_engineer/core/db.py
gpt_engineer/core/domain.py
gpt_engineer/core/steps.py
gpt_engineer/preprompts/clarify
gpt_engineer/preprompts/file_format
gpt_engineer/preprompts/generate
gpt_engineer/preprompts/improve
gpt_engineer/preprompts/philosophy
gpt_engineer/preprompts/roadmap
gpt_engineer-0.1.0.dist-info/LICENSE
gpt_engineer-0.1.0.dist-info/METADATA
gpt_engineer-0.1.0.dist-info/WHEEL
gpt_engineer-0.1.0.dist-info/entry_points.txt
gpt_engineer-0.1.0.dist-info/top_level.txt
gpt_engineer-0.1.0.dist-info/RECORD
