Metadata-Version: 2.1
Name: gpt-engineer
Version: 0.1.0
Summary: Specify what you want it to build, the AI asks for clarification, and then builds it.
Project-URL: Homepage, https://github.com/AntonOsika/gpt-engineer
Project-URL: Bug Tracker, https://github.com/AntonOsika/gpt-engineer/issues
Classifier: Development Status :: 4 - Beta
Classifier: Programming Language :: Python :: 3.8
Classifier: Programming Language :: Python :: 3.9
Classifier: Programming Language :: Python :: 3.10
Classifier: Programming Language :: Python :: 3.11
Classifier: License :: OSI Approved :: MIT License
Classifier: Topic :: Scientific/Engineering :: Artificial Intelligence
Requires-Python: <4.0,>=3.8
License-File: LICENSE
Requires-Dist: black ==23.3.0
Requires-Dist: click >=8.0.0
Requires-Dist: mypy ==1.3.0
Requires-Dist: openai ==0.27.8
Requires-Dist: pre-commit ==3.3.3
Requires-Dist: pytest ==7.3.1
Requires-Dist: ruff ==0.0.272
Requires-Dist: termcolor ==2.3.0
Requires-Dist: typer >=0.3.2
Requires-Dist: rudder-sdk-python ==2.0.2
Requires-Dist: dataclasses-json ==0.5.7
Requires-Dist: tiktoken >=0.0.4
Requires-Dist: tabulate ==0.9.0
Requires-Dist: python-dotenv >=0.21.0
Requires-Dist: langchain >=0.0.240
Requires-Dist: agent-protocol ==1.0.1
Provides-Extra: doc
Requires-Dist: autodoc-pydantic >=1.8.0 ; extra == 'doc'
Requires-Dist: myst-parser >=0.18.1 ; extra == 'doc'
Requires-Dist: nbsphinx >=0.8.9 ; extra == 'doc'
Requires-Dist: sphinx >=4.5.0 ; extra == 'doc'
Requires-Dist: sphinx-autobuild >=2021.3.14 ; extra == 'doc'
Requires-Dist: sphinx-book-theme >=0.3.3 ; extra == 'doc'
Requires-Dist: sphinx-rtd-theme >=1.0.0 ; extra == 'doc'
Requires-Dist: sphinx-typlog-theme >=0.8.0 ; extra == 'doc'
Requires-Dist: sphinx-panels >=0.6.0 ; extra == 'doc'
Requires-Dist: toml >=0.10.2 ; extra == 'doc'
Requires-Dist: myst-nb >=0.17.1 ; extra == 'doc'
Requires-Dist: linkchecker >=10.2.1 ; extra == 'doc'
Requires-Dist: sphinx-copybutton >=0.5.1 ; extra == 'doc'
Requires-Dist: markdown-include >=0.6.0 ; extra == 'doc'
Requires-Dist: sphinx-copybutton >=0.5.2 ; extra == 'doc'
Provides-Extra: test
Requires-Dist: pytest >=7.3.1 ; extra == 'test'
